allowed_ghosts/README.md
allowed_ghosts/__init__.py
allowed_ghosts/_cache.joblib
allowed_ghosts/apps.py
allowed_ghosts/constants.py
allowed_ghosts/main.py
allowed_ghosts/management/__init__.py
allowed_ghosts/management/commands/__init__.py
allowed_ghosts/management/commands/ghosts.py
allowed_ghosts/migrations/__init__.py
allowed_ghosts/src/calendário_hagiológico.txt
allowed_ghosts/tests.py
allowed_ghosts-0.2.6.dist-info/LICENSE
allowed_ghosts-0.2.6.dist-info/METADATA
allowed_ghosts-0.2.6.dist-info/WHEEL
allowed_ghosts-0.2.6.dist-info/RECORD
