Metadata-Version: 2.1
Name: allowed-ghosts
Version: 0.2.6
Summary: Daily inspiration for `ALLOWED_HOSTS` values.
Home-page: https://github.com/JV-conseil/allowed-ghosts
License: EUPL-1.2
Keywords: django
Author: JV conseil
Author-email: contact@jv-conseil.net
Requires-Python: >=3.9.16
Classifier: Development Status :: 5 - Production/Stable
Classifier: Framework :: Django
Classifier: Intended Audience :: Information Technology
Classifier: License :: OSI Approved :: European Union Public Licence 1.2 (EUPL 1.2)
Classifier: Programming Language :: Python :: 3
Classifier: Programming Language :: Python :: 3.10
Classifier: Programming Language :: Python :: 3.11
Requires-Dist: django (>=4,<5.0)
Requires-Dist: joblib (>=1.2.0)
Requires-Dist: unidecode (>=1.3.6)
Project-URL: Bug Tracker, https://github.com/JV-conseil/allowed-ghosts/issues
Project-URL: Documentation, https://jv-conseil.github.io/allowed-ghosts/
Project-URL: Donate, https://www.paypal.com/donate/?hosted_button_id=P3DGL6EANDY96
Project-URL: Repository, https://github.com/JV-conseil/allowed-ghosts
Project-URL: Stack Overflow, https://stackoverflow.com/users/2477854/jv-conseil
Project-URL: Sponsor, https://github.com/sponsors/JV-conseil
Project-URL: Twitter, https://twitter.com/JVconseil
